shimeri/__init__.py
shimeri/psychrometricchart.py
shimeri/psychrometrics.py
shimeri-0.2.0.dist-info/METADATA
shimeri-0.2.0.dist-info/WHEEL
shimeri-0.2.0.dist-info/licenses/LICENSE
shimeri-0.2.0.dist-info/RECORD
